ironic_inspector/__init__.py
ironic_inspector/api_tools.py
ironic_inspector/introspect.py
ironic_inspector/introspection_state.py
ironic_inspector/known_accelerators.yaml
ironic_inspector/main.py
ironic_inspector/node_cache.py
ironic_inspector/policy.py
ironic_inspector/process.py
ironic_inspector/rules.py
ironic_inspector/utils.py
ironic_inspector/version.py
ironic_inspector/wsgi_service.py
ironic_inspector/cmd/__init__.py
ironic_inspector/cmd/all.py
ironic_inspector/cmd/conductor.py
ironic_inspector/cmd/dbsync.py
ironic_inspector/cmd/migration.py
ironic_inspector/cmd/status.py
ironic_inspector/cmd/wsgi.py
ironic_inspector/common/__init__.py
ironic_inspector/common/auth_basic.py
ironic_inspector/common/context.py
ironic_inspector/common/coordination.py
ironic_inspector/common/device_hints.py
ironic_inspector/common/exception.py
ironic_inspector/common/i18n.py
ironic_inspector/common/ironic.py
ironic_inspector/common/keystone.py
ironic_inspector/common/lldp_parsers.py
ironic_inspector/common/lldp_tlvs.py
ironic_inspector/common/locking.py
ironic_inspector/common/mdns.py
ironic_inspector/common/rpc.py
ironic_inspector/common/rpc_service.py
ironic_inspector/common/service_utils.py
ironic_inspector/common/swift.py
ironic_inspector/conductor/__init__.py
ironic_inspector/conductor/manager.py
ironic_inspector/conf/__init__.py
ironic_inspector/conf/accelerators.py
ironic_inspector/conf/capabilities.py
ironic_inspector/conf/coordination.py
ironic_inspector/conf/default.py
ironic_inspector/conf/discovery.py
ironic_inspector/conf/dnsmasq_pxe_filter.py
ironic_inspector/conf/exception.py
ironic_inspector/conf/extra_hardware.py
ironic_inspector/conf/healthcheck.py
ironic_inspector/conf/iptables.py
ironic_inspector/conf/ironic.py
ironic_inspector/conf/mdns.py
ironic_inspector/conf/opts.py
ironic_inspector/conf/pci_devices.py
ironic_inspector/conf/port_physnet.py
ironic_inspector/conf/processing.py
ironic_inspector/conf/pxe_filter.py
ironic_inspector/conf/service_catalog.py
ironic_inspector-12.5.0.dist-info/AUTHORS
ironic_inspector-12.5.0.dist-info/LICENSE
ironic_inspector-12.5.0.dist-info/METADATA
ironic_inspector-12.5.0.dist-info/WHEEL
ironic_inspector-12.5.0.dist-info/entry_points.txt
ironic_inspector-12.5.0.dist-info/pbr.json
ironic_inspector-12.5.0.dist-info/top_level.txt
ironic_inspector-12.5.0.dist-info/RECORD
