Metadata-Version: 2.1
Name: ironic-inspector
Version: 12.5.0
Summary: Hardware introspection for OpenStack Bare Metal
Home-page: https://docs.openstack.org/ironic-inspector/latest/
Author: OpenStack
Author-email: openstack-discuss@lists.openstack.org
License: Apache-2
Classifier: Environment :: Console
Classifier: Environment :: OpenStack
Classifier: Intended Audience :: System Administrators
Classifier: Intended Audience :: Information Technology
Classifier: License :: OSI Approved :: Apache Software License
Classifier: Operating System :: OS Independent
Classifier: Programming Language :: Python
Classifier: Programming Language :: Python :: Implementation :: CPython
Classifier: Programming Language :: Python :: 3 :: Only
Classifier: Programming Language :: Python :: 3
Classifier: Programming Language :: Python :: 3.10
Classifier: Programming Language :: Python :: 3.11
Classifier: Programming Language :: Python :: 3.12
Requires-Python: >=3.9
License-File: LICENSE
License-File: AUTHORS
Requires-Dist: automaton >=1.9.0
Requires-Dist: alembic >=1.4.2
Requires-Dist: construct >=2.9.39
Requires-Dist: eventlet >=0.27.0
Requires-Dist: Flask >=1.1.0
Requires-Dist: futurist >=1.2.0
Requires-Dist: jsonpath-rw >=1.2.0
Requires-Dist: jsonschema >=3.2.0
Requires-Dist: keystoneauth1 >=4.2.0
Requires-Dist: keystonemiddleware >=4.18.0
Requires-Dist: netaddr >=0.7.18
Requires-Dist: pbr >=3.1.1
Requires-Dist: PyYAML >=5.3.1
Requires-Dist: openstacksdk >=0.40.0
Requires-Dist: oslo.concurrency >=3.26.0
Requires-Dist: oslo.config >=6.8.0
Requires-Dist: oslo.context >=2.22.0
Requires-Dist: oslo.db >=12.1.0
Requires-Dist: oslo.i18n >=3.20.0
Requires-Dist: oslo.log >=4.3.0
Requires-Dist: oslo.messaging >=14.1.0
Requires-Dist: oslo.middleware >=3.31.0
Requires-Dist: oslo.policy >=4.5.0
Requires-Dist: oslo.rootwrap >=5.8.0
Requires-Dist: oslo.serialization >=2.25.0
Requires-Dist: oslo.service >=1.31.0
Requires-Dist: oslo.upgradecheck >=1.2.0
Requires-Dist: oslo.utils >=4.5.0
Requires-Dist: tenacity >=6.2.0
Requires-Dist: stevedore >=1.20.0
Requires-Dist: SQLAlchemy >=1.4.0
Requires-Dist: tooz >=2.5.1
Requires-Dist: microversion-parse >=1.0.1
Requires-Dist: zeroconf >=0.24.0
Requires-Dist: bcrypt >=3.1.3
